{"assets":{"C0ECD554A75AC5304C2105481E38A6E0":{"type":"texture","index":1,"url":{"native":"assets\/54EABEF0-7B1F-44A2-89EE-0D80E38C8CE5.pdf"},"width":1920,"height":1080},"A7BA2CCB7B3BED7956E0EB513AB88BDE":{"type":"texture","index":0,"url":{"native":"assets\/54EABEF0-7B1F-44A2-89EE-0D80E38C8CE5.pdf"},"width":1920,"height":1080}},"events":[{"effects":[{"beginTime":0,"baseLayer":{"animations":[],"initialState":{"affineTransform":[1,0,0,1,0,0],"masksToBounds":false,"rotation":0,"scale":1,"position":{"pointX":960,"pointY":540},"width":1920,"sublayerTransform":[1,0,0,0,0,1,0,0,0,0,1,0,0,0,0,1],"contentsRect":{"y":0,"x":0,"width":1,"height":1},"opacity":1,"edgeAntialiasingMask":251658240,"height":1080,"hidden":false,"anchorPoint":{"pointX":0.5,"pointY":0.5}},"objectID":"0","layers":[{"animations":[],"initialState":{"affineTransform":[1,0,0,1,0,0],"masksToBounds":false,"rotation":0,"scale":1,"position":{"pointX":960,"pointY":540},"width":1920,"sublayerTransform":[1,0,0,0,0,1,0,0,0,0,1,-0.00035007912466775983,0,0,0,1],"contentsRect":{"y":0,"x":0,"width":1,"height":1},"opacity":1,"edgeAntialiasingMask":251658240,"height":1080,"hidden":false,"anchorPoint":{"pointX":0.5,"pointY":0.5}},"layers":[{"animations":[],"layers":[],"texturedRectangle":{"isBackgroundTexture":false,"singleTextureOpacity":1,"textureType":0,"textBaseline":0,"textXHeight":0,"isVerticalText":false},"initialState":{"affineTransform":[1,0,0,1,0,0],"masksToBounds":false,"rotation":0,"scale":1,"position":{"pointX":960,"pointY":540},"width":1920,"sublayerTransform":[1,0,0,0,0,1,0,0,0,0,1,0,0,0,0,1],"contentsRect":{"y":0,"x":0,"width":1,"height":1},"opacity":1,"edgeAntialiasingMask":0,"height":1080,"hidden":false,"anchorPoint":{"pointX":0.5,"pointY":0.5}},"texture":"C0ECD554A75AC5304C2105481E38A6E0"},{"animations":[{"additive":false,"timeOffset":0,"beginTime":0,"from":{"scalar":false},"repeatCount":0,"fillMode":"both","duration":0.01,"autoreverses":false,"property":"hidden","to":{"scalar":true},"removedOnCompletion":false}],"layers":[],"texturedRectangle":{"isBackgroundTexture":false,"singleTextureOpacity":1,"textureType":0,"textBaseline":0,"textXHeight":0,"isVerticalText":false},"initialState":{"affineTransform":[1,0,0,1,0,0],"masksToBounds":false,"rotation":0,"scale":1,"position":{"pointX":960,"pointY":540},"width":1920,"sublayerTransform":[1,0,0,0,0,1,0,0,0,0,1,0,0,0,0,1],"contentsRect":{"y":0,"x":0,"width":1,"height":1},"opacity":1,"edgeAntialiasingMask":0,"height":1080,"hidden":false,"anchorPoint":{"pointX":0.5,"pointY":0.5}},"texture":"A7BA2CCB7B3BED7956E0EB513AB88BDE"}]}]},"effects":[],"duration":0.01,"type":"transition","attributes":{"direction":0},"name":"none","objectID":"0"}],"automaticPlay":false,"hyperlinks":[],"accessibility":[{"text":"pmeasyr \/ pypmsi ","targetRectangle":{"y":-0.63361835479736328,"x":43.514071941375732,"width":846.73779296875,"height":94}},{"text":"des communs en santé pour l’information ","targetRectangle":{"y":93.366381645202637,"x":108.99438810348511,"width":1368.22265625,"height":64}},{"text":"médicale des établissements ","targetRectangle":{"y":157.36638164520264,"x":108.99438810348511,"width":957.755859375,"height":64}},{"text":"et plus si affinités","targetRectangle":{"y":221.36638164520264,"x":108.99438810348511,"width":684.111328125,"height":64}},{"text":"image-collée.tiff","targetRectangle":{"y":347.65625,"x":229.58183288574222,"width":384.70189623196347,"height":384.70189623196347}},{"text":"image-collée.tiff","targetRectangle":{"y":732.66391086578369,"x":888.5838623046875,"width":203.51791381835938,"height":152.638427734375}},{"text":"image-collée.tiff","targetRectangle":{"y":724.7694091796875,"x":1111.4010620117188,"width":165.35751342773438,"height":152.5460205078125}},{"text":"image-collée.tiff","targetRectangle":{"y":350.9747314453125,"x":766.41717529296875,"width":378.05050659179688,"height":378.05050659179688}},{"text":"vidéo-collée.png","targetRectangle":{"y":347.65625,"x":1296.6156005859375,"width":384.6875,"height":384.6875}},{"text":"image-collée.tiff","targetRectangle":{"y":724.7694091796875,"x":1286.4373168945312,"width":159.46244812011719,"height":159.46243286132812}},{"text":"image-collée.tiff","targetRectangle":{"y":736.63523578643799,"x":735.1934814453125,"width":135.73088073730469,"height":135.73086547851562}},{"text":"vidéo-collée.png","targetRectangle":{"y":-9.8599977493286133,"x":1576.9190673828125,"width":330.62075805664062,"height":330.62075805664062}},{"text":"2024-03-26 - Saint-Jacut-de-la-Mer","targetRectangle":{"y":1010.8530883789062,"x":723.63337392807,"width":475.35000000000002,"height":41}},{"text":"CHU-BREST_LOGO-2021_RVB.png","targetRectangle":{"y":736.63513565063477,"x":476.71697998046875,"width":229.07273864746094,"height":135.73095703125}},{"text":"Guillaume Pressiat, Département des Données de Santé, CHU de Brest","targetRectangle":{"y":919.0465087890625,"x":402.77536718749991,"width":1112.7520000000004,"height":46}}],"baseLayer":{"animations":[],"initialState":{"affineTransform":[1,0,0,1,0,0],"masksToBounds":false,"rotation":0,"scale":1,"position":{"pointX":960,"pointY":540},"width":1920,"sublayerTransform":[1,0,0,0,0,1,0,0,0,0,1,0,0,0,0,1],"contentsRect":{"y":0,"x":0,"width":1,"height":1},"opacity":1,"edgeAntialiasingMask":251658240,"height":1080,"hidden":false,"anchorPoint":{"pointX":0.5,"pointY":0.5}},"objectID":"0","layers":[{"animations":[],"initialState":{"affineTransform":[1,0,0,1,0,0],"masksToBounds":false,"rotation":0,"scale":1,"position":{"pointX":960,"pointY":540},"width":1920,"sublayerTransform":[1,0,0,0,0,1,0,0,0,0,1,-0.00035007912466775983,0,0,0,1],"contentsRect":{"y":0,"x":0,"width":1,"height":1},"opacity":1,"edgeAntialiasingMask":251658240,"height":1080,"hidden":false,"anchorPoint":{"pointX":0.5,"pointY":0.5}},"layers":[{"animations":[],"layers":[],"texturedRectangle":{"isBackgroundTexture":false,"singleTextureOpacity":1,"textureType":0,"textBaseline":0,"textXHeight":0,"isVerticalText":false},"initialState":{"affineTransform":[1,0,0,1,0,0],"masksToBounds":false,"rotation":0,"scale":1,"position":{"pointX":960,"pointY":540},"width":1920,"sublayerTransform":[1,0,0,0,0,1,0,0,0,0,1,0,0,0,0,1],"contentsRect":{"y":0,"x":0,"width":1,"height":1},"opacity":1,"edgeAntialiasingMask":0,"height":1080,"hidden":false,"anchorPoint":{"pointX":0.5,"pointY":0.5}},"texture":"A7BA2CCB7B3BED7956E0EB513AB88BDE"}]}]}}]}